tools/__init__.py
tools/version.py
tools/apis/__init__.py
tools/apis/anime/__init__.py
tools/apis/anime/anime_api_version.py
tools/apis/anime/format_results.py
tools/apis/anime/gogoanimeapi.py
tools/apis/anime/kissmangaapi.py
pyrunaway-0.0.1.dev0.dist-info/METADATA
pyrunaway-0.0.1.dev0.dist-info/WHEEL
pyrunaway-0.0.1.dev0.dist-info/top_level.txt
pyrunaway-0.0.1.dev0.dist-info/RECORD
